echo/__init__.py
echo/datastore/__init__.py
echo/datastore/db.py
echo/datastore/db_utils.py
echo/datastore/entity.py
echo/datastore/errors.py
echo/datastore/properties.py
echo_datastore_entities-0.0.9.dist-info/METADATA
echo_datastore_entities-0.0.9.dist-info/WHEEL
echo_datastore_entities-0.0.9.dist-info/top_level.txt
echo_datastore_entities-0.0.9.dist-info/RECORD
