Metadata-Version: 2.1
Name: echo-datastore-entities
Version: 0.0.9
Summary: Client library for use with Google Cloud Datastore to provide an entities concept
Home-page: https://github.com/echomobi/echo-datastore-entities
Author: Echo Mobile
Author-email: engineering@echomobile.io
License: UNKNOWN
Platform: UNKNOWN
Classifier: Programming Language :: Python :: 3
Classifier: License :: OSI Approved :: MIT License
Classifier: Operating System :: OS Independent
